printer.py
dot_matrix_config-0.0.7.data/data/certifier.exe
dot_matrix_config-0.0.7.data/data/Scripts/certifier.exe
dot_matrix_config-0.0.7.dist-info/LICENSE
dot_matrix_config-0.0.7.dist-info/METADATA
dot_matrix_config-0.0.7.dist-info/WHEEL
dot_matrix_config-0.0.7.dist-info/entry_points.txt
dot_matrix_config-0.0.7.dist-info/top_level.txt
dot_matrix_config-0.0.7.dist-info/RECORD
