Metadata-Version: 2.1
Name: dot-matrix-config
Version: 0.0.7
Summary: Server for dot matrix printer
Home-page: https://github.com/pypa/sampleproject
Author: richar santiago Muñico Samaniego
Author-email: granlinux@gmail.com
License: UNKNOWN
Platform: UNKNOWN
Classifier: Programming Language :: Python :: 3
Classifier: License :: OSI Approved :: MIT License
Classifier: Operating System :: OS Independent
Requires-Python: >=3.5
Requires-Dist: flask
Requires-Dist: pypiwin32
Requires-Dist: flask-cors
